Metadata-Version: 1.1
Name: waves-demo
Version: 1.1.1
Summary: WebApp for Versatile and Easy bio-informatics Services
Home-page: https://github.com/lirmm/waves-demo
Author: LIRMM - MAB Laboratory - France
Author-email: vincent.lefort@lirmm.fr
License: GPL-v3
Platform: UNKNOWN
Classifier: Environment :: Web Environment
Classifier: Framework :: Django
Classifier: Development Status :: 4 - Beta
Classifier: Intended Audience :: Developers
Classifier: License :: OSI Approved :: GNU General Public License v3 (GPLv3)
Classifier: Programming Language :: Python :: 2.7
Classifier: Topic :: Utilities
Classifier: Topic :: System :: Distributed Computing
Classifier: Topic :: Internet :: WWW/HTTP :: WSGI :: Application
Classifier: Topic :: Scientific/Engineering :: Bio-Informatics
Classifier: Operating System :: Unix
